azure/media/videoanalyzeredge/__init__.py
azure/media/videoanalyzeredge/_version.py
azure/media/videoanalyzeredge/_generated/__init__.py
azure/media/videoanalyzeredge/_generated/_vendor.py
azure/media/videoanalyzeredge/_generated/_version.py
azure/media/videoanalyzeredge/_generated/models/__init__.py
azure/media/videoanalyzeredge/_generated/models/_azure_video_analyzerfor_edge_enums.py
azure/media/videoanalyzeredge/_generated/models/_models.py
azure/media/videoanalyzeredge/_generated/models/_models_py3.py
azure_media_videoanalyzer_edge-1.0.0b4.dist-info/LICENSE
azure_media_videoanalyzer_edge-1.0.0b4.dist-info/METADATA
azure_media_videoanalyzer_edge-1.0.0b4.dist-info/WHEEL
azure_media_videoanalyzer_edge-1.0.0b4.dist-info/top_level.txt
azure_media_videoanalyzer_edge-1.0.0b4.dist-info/RECORD
