Metadata-Version: 2.1
Name: azure-media-videoanalyzer-edge
Version: 1.0.0b4
Summary: Azure Video Analyzer Edge SDK Library for Python
Home-page: https://github.com/Azure/azure-sdk-for-python/tree/main/sdk/videoanalyzer/azure-media-videoanalyzer-edge
Author: Microsoft Corporation
Author-email: azpysdkhelp@microsoft.com
License: MIT License
Platform: UNKNOWN
Classifier: Development Status :: 4 - Beta
Classifier: Programming Language :: Python
Classifier: Programming Language :: Python :: 2
Classifier: Programming Language :: Python :: 2.7
Classifier: Programming Language :: Python :: 3
Classifier: Programming Language :: Python :: 3.6
Classifier: Programming Language :: Python :: 3.7
Classifier: Programming Language :: Python :: 3.8
Classifier: Programming Language :: Python :: 3.9
Classifier: License :: OSI Approved :: MIT License
Requires-Dist: msrest (>=0.6.21)
Requires-Dist: azure-core (<2.0.0,>=1.2.2)
Requires-Dist: azure-media-nspkg ; python_version<'3.0'
Requires-Dist: enum34 (>=1.0.4) ; python_version<'3.4'
Requires-Dist: typing ; python_version<'3.5'
